{"BRIDGE_ALLOWED_ARTIFACT_KINDS":["SUBPROOF_BUNDLE_V1","PATCH_BUNDLE_V1","ONTOLOGY_PATCH_V1"],"BRIDGE_ENABLED":true,"BRIDGE_EXCHANGE_DIRNAME":"bridge_exchange","BRIDGE_MAX_IMPORT_ACCEPTS_PER_EPOCH":16,"BRIDGE_MAX_OFFERS_PUBLISH_PER_EPOCH":16,"IMMUTABLE_CORE_LOCK_REL":"meta-core/meta_constitution/v4_0/immutable_core_lock_v1.json","IMMUTABLE_CORE_REQUIRED":true,"META_ALLOWED_POLICY_KEYS":["bridge.subscriptions_add","task.priority_boost"],"META_ALLOWED_UPDATE_KINDS":["KNOWLEDGE_ASSERTION_ADD_V1","POLICY_PATCH_V1"],"META_CONSENSUS_POLICY":"HOLO_CONSENSUS_V1","META_EXCHANGE_DIRNAME":"meta_exchange","META_LEDGER_ENABLED":true,"OMEGA_ALLOWED_PROPOSAL_SYSTEMS":["autonomy_v2","recursive_ontology_v2_1","csi_v2_2","hardening_v2_3"],"OMEGA_ENABLED":true,"OMEGA_FORBIDDEN_LEAK_FIELDS":["expected_answer","unit_test_expected_stdout","unit_test_expected_files","proof_target","ground_truth"],"OMEGA_UNBOUNDED_EPOCHS":true,"SPEC_VERSION":"v4_0","SUBSWARM_ENABLED":true,"SUBSWARM_JOIN_TIMEOUT_EPOCHS":12,"SUBSWARM_MAX_CHILDREN_PER_PARENT_TASK":16,"SUBSWARM_MAX_DEPTH":16,"SUBSWARM_MAX_JOINS_PER_EPOCH":16,"SUBSWARM_MAX_SPAWNS_PER_EPOCH":16,"SUBSWARM_MAX_TOTAL_NODES":512,"SWARM_BARRIER_ALPHA_DEN":20,"SWARM_BARRIER_ALPHA_NUM":19,"SWARM_COMMIT_POLICY":"ROUND_COMMIT_V4_HOLOGRAPHIC","SWARM_EXPORT_MAX_ITEMS":256,"SWARM_FATAL_REASONS_V3_3":["SCHEMA_INVALID","META_DRIFT","CANON_HASH_MISMATCH","MISSING_ARTIFACT","PATH_TRAVERSAL","IMMUTABLE_CORE_ATTESTATION_MISSING","IMMUTABLE_CORE_ATTESTATION_INVALID","SWARM_AGENT_ATTESTATION_MISMATCH","SWARM_LEDGER_HASH_MISMATCH","SWARM_EVENT_REFERENCE_MISSING","BARRIER_LEDGER_HASH_MISMATCH","BARRIER_CONTINUITY_MISMATCH","SUBSWARM_PARENT_LINK_MISMATCH","SUBSWARM_DUPLICATE_JOIN","SUBSWARM_CYCLE_DETECTED","SUBSWARM_NODE_LIMIT_EXCEEDED","SUBSWARM_DEPTH_LIMIT_EXCEEDED","STALE_BASE_BARRIER_UPDATE","NONDETERMINISM","BRIDGE_WRONG_ROOT","BRIDGE_ICORE_MISMATCH","BRIDGE_OFFER_HASH_MISMATCH","BRIDGE_BLOB_HASH_MISMATCH","BRIDGE_UNVERIFIED_EXPORT","BRIDGE_NONLOCAL_EVIDENCE","BRIDGE_DUPLICATE_ACCEPT","BRIDGE_PUBLISHER_UNKNOWN","BRIDGE_PUBLISHER_NOT_VALID","STALE_CONTEXT_BARRIER_UPDATE","BARRIER_EVIDENCE_AMBIGUOUS","BARRIER_EVIDENCE_MISSING","META_WRONG_ROOT","META_ICORE_MISMATCH","META_HASH_MISMATCH","META_UNVERIFIED_UPDATE","META_LATENCY_VIOLATION","META_POLICY_OUT_OF_BOUNDS","META_HEAD_MISMATCH","META_POLICY_IMPORT_VIOLATION"],"SWARM_MAX_ACCEPTS_PER_EPOCH":8,"SWARM_MAX_AGENTS":32,"SWARM_MAX_EPOCHS":256,"SWARM_MAX_TASKS_PER_EPOCH":256,"SWARM_PROTOCOL_VERSION":"swarm_protocol_v4_holographic","SWARM_RETRYABLE_REASONS_V3_3":["TASK_UNASSIGNABLE","TASK_EXEC_FAIL","TASK_VERIFY_FAIL","SUBSWARM_NOT_READY","SUBSWARM_TIMEOUT"]}
