{"branch_signature":"sha256:1c4c58cde68b85d6e556e4603a63962ad61178e4fef46368611a2806b1011204","budget_verdict":"OK","case_id":"sha256:7b35fa47a610f2748804404538f358019f1f9715c362178b15adb4b8b823a552","explain_hash":"sha256:2832865adf65b556fed40915c5efe2f63d02a86dc2a349dafff9f2c2358e48b2","rule_path":[{"outcome":"kept=3;dropped=2","rule_id":"R0_FILTER_ENABLED"},{"outcome":"kept=1;dropped=2","rule_id":"R1_FILTER_COOLDOWN"},{"outcome":"hard_stop=false","rule_id":"R2_BUDGET_HARD_STOP"},{"outcome":"remaining=421>=min=301","rule_id":"R3_BUDGET_MIN_REMAINING"},{"outcome":"kept=0;dropped=1","rule_id":"R4_FILTER_COST_MAX"},{"outcome":"top_priority=NONE","rule_id":"R5_SCORE_PRIORITY"},{"outcome":"no_candidates","rule_id":"R6_TIEBREAK"}],"schema_version":"brain_decision_v1","selected_campaign_id":null,"selected_capability_id":null,"verdict":"SKIP"}
