{"CTX_HASH_CACHE_V1_MAX_CAPACITY":65536,"DEMON_V4_EVAL_MACRO_EVERY_N_EPOCHS":2,"DEMON_V4_EVAL_METABOLISM_EVERY_N_EPOCHS":2,"DEMON_V4_EVAL_ONTO_EVERY_N_EPOCHS":2,"MACRO_V2_CTX_MDL_GAIN_MIN_BITS":2048,"MACRO_V2_EVICT_K_DROP":2,"MACRO_V2_MAX_GUARD_CTX":256,"MACRO_V2_SUPPORT_FAMILIES_MIN":3,"MACRO_V2_WINDOW_EPOCHS":2,"METAPATCH_V1_MIN_SHA256_CALL_DELTA":1,"ONTO_V3_DL_GAIN_MIN_BITS":8192,"ONTO_V3_MAX_CONCEPTS":256,"ONTO_V3_MAX_CTX_ARITY":8,"ONTO_V3_SUPPORT_FAMILIES_MIN":3,"ONTO_V3_TRAIN_STOP_GAIN_BITS_LT":64,"ONTO_V3_WINDOW_EPOCHS":2}
